clock_gating_FSM.v
`timescale 1ns / 1ps
//////////////////////////////////////////////////////////////////////////////////
// Company: 
// Engineer: 
// 
// Create Date: 07.06.2025 18:36:07
// Design Name: 
// Module Name: clock_gating_FSM
// Project Name: 
// Target Devices: 
// Tool Versions: 
// Description: Clock Gating FSM with Safe Implementation
// 
// Dependencies: 
// 
// Revision:
// Revision 0.01 - File Created with Improvements
// Additional Comments: 
// - Improved clock gating safety
// - Better synthesis compatibility
// - Enhanced testbench
//////////////////////////////////////////////////////////////////////////////////

`timescale 1ns / 1ps
//////////////////////////////////////////////////////////////////////////////////
// Company: 
// Engineer: 
// 
// Create Date: 07.06.2025 18:36:07
// Design Name: 
// Module Name: clock_gating_FSM
// Project Name: 
// Target Devices: 
// Tool Versions: 
// Description: Clock Gating FSM with Safe Implementation
// 
// Dependencies: 
// 
// Revision:
// Revision 0.01 - File Created with Synthesis Fixes
// Additional Comments: 
// - Fixed synthesis warnings
// - Removed unused modules
// - Improved synthesis compatibility
//////////////////////////////////////////////////////////////////////////////////

// Clock Gating FSM - Synthesis-Clean Implementation
`timescale 1ns / 1ps

//=============================================================================
// Main Clock Gating FSM Module
//=============================================================================
module clock_gating_FSM(
    input wire clk,
    input wire rst,
    input wire trig,
    output reg enable_clk,
    output wire gated_clk,
    output wire [1:0] current_state
);
    
    // State encoding - Using Gray code for better switching
    localparam IDLE   = 2'b00;
    localparam ACTIVE = 2'b01;
    localparam WAIT   = 2'b11;
    localparam SLEEP  = 2'b10;
    
    // Internal state registers
    reg [1:0] state, next_state;
    reg enable_clk_ff;  // Registered enable for safer clock gating
    
    // Sequential logic - State register
    always @(posedge clk or posedge rst) begin
        if (rst)
            state <= IDLE;
        else
            state <= next_state;
    end
    
    // Combinational logic - Next state logic
    always @(*) begin
        case(state)
            IDLE:   next_state = trig ? ACTIVE : IDLE;
            ACTIVE: next_state = trig ? ACTIVE : WAIT;
            WAIT:   next_state = trig ? ACTIVE : SLEEP;
            SLEEP:  next_state = trig ? ACTIVE : SLEEP;
            default: next_state = IDLE;  // Safe default
        endcase
    end
    
    // Output logic - Moore FSM (output depends only on current state)
    always @(*) begin
        case(state)
            ACTIVE, WAIT: enable_clk = 1'b1;
            IDLE, SLEEP:  enable_clk = 1'b0;
            default:      enable_clk = 1'b0;  // Safe default
        endcase
    end
    
    // Safe clock gating using registered enable (eliminates glitches)
    always @(posedge clk or posedge rst) begin
        if (rst)
            enable_clk_ff <= 1'b0;
        else
            enable_clk_ff <= enable_clk;
    end
    
    // Generate gated clock - Use registered enable for safety
    assign gated_clk = clk & enable_clk_ff;
    assign current_state = state;
    
endmodule

//=============================================================================
// Example Load Module (demonstrates clock gating benefit)
//=============================================================================
module example_load(
    input wire clk,
    input wire rst,
    input wire enable,
    output reg [7:0] counter
);
    
    always @(posedge clk or posedge rst) begin
        if (rst)
            counter <= 8'b0;
        else if (enable)
            counter <= counter + 1;
    end
    
endmodule

//=============================================================================
// Power Monitor Module (estimates power savings)
//=============================================================================
module power_monitor(
    input wire clk,
    input wire rst,
    input wire normal_clk_active,
    input wire gated_clk_active,
    output reg [15:0] normal_clk_cycles,
    output reg [15:0] gated_clk_cycles,
    output wire [7:0] power_savings_percent
);
    
    // Count clock cycles
    always @(posedge clk or posedge rst) begin
        if (rst) begin
            normal_clk_cycles <= 16'b0;
            gated_clk_cycles <= 16'b0;
        end else begin
            if (normal_clk_active)
                normal_clk_cycles <= normal_clk_cycles + 1;
            if (gated_clk_active)
                gated_clk_cycles <= gated_clk_cycles + 1;
        end
    end
    
    // Calculate power savings percentage (simplified)
    wire [15:0] savings = normal_clk_cycles - gated_clk_cycles;
    assign power_savings_percent = (normal_clk_cycles > 0) ? 
                                   (savings * 100 / normal_clk_cycles) : 8'b0;
    
endmodule

//=============================================================================
// Top Module - Complete System with Power Monitoring
//=============================================================================
module clock_gating_top(
    input wire clk,
    input wire rst,
    input wire trig,
    output wire [7:0] counter_normal,
    output wire [7:0] counter_gated,
    output wire [1:0] fsm_state,
    output wire clock_enabled,
    output wire [7:0] power_savings_percent,
    output wire [15:0] normal_cycles,
    output wire [15:0] gated_cycles
);
    
    wire gated_clk;
    wire enable_clk;
    wire [15:0] normal_clk_cycles, gated_clk_cycles;
    
    // Clock gating FSM
    clock_gating_FSM fsm_inst (
        .clk(clk),
        .rst(rst),
        .trig(trig),
        .enable_clk(enable_clk),
        .gated_clk(gated_clk),
        .current_state(fsm_state)
    );
    
    // Normal counter (always running)
    example_load normal_counter (
        .clk(clk),
        .rst(rst),
        .enable(1'b1),
        .counter(counter_normal)
    );
    
    // Gated counter (only runs when clock is enabled)
    example_load gated_counter (
        .clk(gated_clk),
        .rst(rst),
        .enable(1'b1),
        .counter(counter_gated)
    );
    
    // Power monitoring
    power_monitor pwr_mon (
        .clk(clk),
        .rst(rst),
        .normal_clk_active(1'b1),
        .gated_clk_active(enable_clk),
        .normal_clk_cycles(normal_clk_cycles),
        .gated_clk_cycles(gated_clk_cycles),
        .power_savings_percent(power_savings_percent)
    );
    
    // Output assignments
    assign clock_enabled = enable_clk;
    assign normal_cycles = normal_clk_cycles;
    assign gated_cycles = gated_clk_cycles;
    
endmodule

//=============================================================================
// Comprehensive Testbench
//=============================================================================
module tb_clock_gating;
    
    reg clk, rst, trig;
    wire [7:0] counter_normal, counter_gated;
    wire [1:0] fsm_state;
    wire clock_enabled;
    wire [7:0] power_savings;
    wire [15:0] normal_cycles, gated_cycles;
    
    // Instantiate top module
    clock_gating_top dut (
        .clk(clk),
        .rst(rst),
        .trig(trig),
        .counter_normal(counter_normal),
        .counter_gated(counter_gated),
        .fsm_state(fsm_state),
        .clock_enabled(clock_enabled),
        .power_savings_percent(power_savings),
        .normal_cycles(normal_cycles),
        .gated_cycles(gated_cycles)
    );
    
    // Clock generation - 100MHz (10ns period)
    initial clk = 0;
    always #5 clk = ~clk;
    
    // State names for display
    reg [63:0] state_name;
    always @(*) begin
        case(fsm_state)
            2'b00: state_name = "IDLE   ";
            2'b01: state_name = "ACTIVE ";
            2'b11: state_name = "WAIT   ";
            2'b10: state_name = "SLEEP  ";
            default: state_name = "UNKNOWN";
        endcase
    end
    
    // Test sequence
    initial begin
        // Initialize
        rst = 1;
        trig = 0;
        
        #20 rst = 0;
        
        $display("\n=== Clock Gating FSM Test ===");
        $display("Testing Clock Gating Implementation");
        
        // Test sequence: Basic operation
        #10 trig = 1;  // Go to ACTIVE
        #30 trig = 0;  // Go to WAIT
        #20;           // Go to SLEEP
        #40;           // Stay in SLEEP
        
        #10 trig = 1;  // Wake up to ACTIVE
        #20 trig = 0;  // Go to WAIT
        #10 trig = 1;  // Back to ACTIVE
        #30 trig = 0;  // Go to WAIT then SLEEP
        #50;           // Stay in SLEEP
        
        $display("\n=== Test Complete ===");
        $display("Final Power Savings: %0d%%", power_savings);
        $display("Normal Cycles: %0d, Gated Cycles: %0d", normal_cycles, gated_cycles);
        $finish;
    end
    
    // Monitor output using $monitor
    initial begin
        $monitor("Time=%0t | State=%s | Trig=%b | ClkEn=%b | Normal=%3d | Gated=%3d | Savings=%3d%%", 
                 $time, state_name, trig, clock_enabled, counter_normal, counter_gated, power_savings);
    end
    
    // Waveform dump for debugging
    initial begin
        $dumpfile("clock_gating.vcd");
        $dumpvars(0, tb_clock_gating);
    end
    
endmodule

clock_gating_FSM.sim/sim_1/behav/xsim/clock_gating.vcd
$date
   Sat Jun  7 22:43:15 2025
$end
$version
  2022.2
$end
$timescale
  1ps
$end
$scope module tb_clock_gating $end
$var reg 1 ! clk $end
$var reg 1 " rst $end
$var reg 1 # trig $end
$var wire 8 $ counter_normal [7:0] $end
$var wire 8 % counter_gated [7:0] $end
$var wire 2 & fsm_state [1:0] $end
$var wire 1 ' clock_enabled $end
$var wire 8 ( power_savings [7:0] $end
$var wire 16 ) normal_cycles [15:0] $end
$var wire 16 * gated_cycles [15:0] $end
$var reg 64 + state_name [63:0] $end
$scope module dut $end
$var wire 1 , clk $end
$var wire 1 - rst $end
$var wire 1 . trig $end
$var wire 8 $ counter_normal [7:0] $end
$var wire 8 % counter_gated [7:0] $end
$var wire 2 & fsm_state [1:0] $end
$var wire 1 ' clock_enabled $end
$var wire 8 ( power_savings_percent [7:0] $end
$var wire 16 ) normal_cycles [15:0] $end
$var wire 16 * gated_cycles [15:0] $end
$var wire 1 / gated_clk $end
$var wire 1 0 enable_clk $end
$var wire 16 1 normal_clk_cycles [15:0] $end
$var wire 16 2 gated_clk_cycles [15:0] $end
$scope module fsm_inst $end
$var wire 1 , clk $end
$var wire 1 - rst $end
$var wire 1 . trig $end
$var reg 1 3 enable_clk $end
$var wire 1 / gated_clk $end
$var wire 2 & current_state [1:0] $end
$var reg 2 4 state [1:0] $end
$var reg 2 5 next_state [1:0] $end
$var reg 1 6 enable_clk_ff $end
$upscope $end
$scope module normal_counter $end
$var wire 1 , clk $end
$var wire 1 - rst $end
$var wire 1 7 enable $end
$var reg 8 8 counter [7:0] $end
$upscope $end
$scope module gated_counter $end
$var wire 1 / clk $end
$var wire 1 - rst $end
$var wire 1 9 enable $end
$var reg 8 : counter [7:0] $end
$upscope $end
$scope module pwr_mon $end
$var wire 1 , clk $end
$var wire 1 - rst $end
$var wire 1 ; normal_clk_active $end
$var wire 1 0 gated_clk_active $end
$var reg 16 < normal_clk_cycles [15:0] $end
$var reg 16 = gated_clk_cycles [15:0] $end
$var wire 8 ( power_savings_percent [7:0] $end
$var wire 16 > savings [15:0] $end
$upscope $end
$upscope $end
$upscope $end
$enddefinitions $end
#0
$dumpvars
0!
1"
0#
b0 $
b0 %
b0 &
0'
b0 (
b0 )
b0 *
b1001001010001000100110001000101001000000010000000100000 +
0,
1-
0.
0/
00
b0 1
b0 2
03
b0 4
b0 5
06
17
b0 8
19
b0 :
1;
b0 <
b0 =
b0 >
$end
#5000
1!
1,
0/
#10000
0!
0,
0/
#15000
1!
1,
0/
#20000
0!
0"
0,
0-
0/
#25000
1!
b1 $
b1100100 (
b1 )
1,
0/
b1 1
b1 8
b1 <
b1 >
#30000
0!
1#
0,
1.
0/
b1 5
#35000
1!
b10 $
b1 &
1'
b1100100 (
b10 )
b1000001010000110101010001001001010101100100010100100000 +
1,
0/
10
b10 1
13
b1 4
b10 8
b10 <
b10 >
#40000
0!
0,
0/
#45000
1!
b11 $
b1 %
b1000010 (
b11 )
b1 *
1,
1/
b11 1
b1 2
16
b11 8
b1 :
b11 <
b1 =
b10 >
#50000
0!
0,
0/
#55000
1!
b100 $
b10 %
b110010 (
b100 )
b10 *
1,
1/
b100 1
b10 2
b100 8
b10 :
b100 <
b10 =
b10 >
#60000
0!
0#
0,
0.
0/
b11 5
#65000
1!
b101 $
b11 %
b11 &
b101000 (
b101 )
b11 *
b1010111010000010100100101010100001000000010000000100000 +
1,
1/
b101 1
b11 2
13
b11 4
b10 5
b101 8
b11 :
b101 <
b11 =
b10 >
#70000
0!
0,
0/
#75000
1!
b110 $
b100 %
b10 &
0'
b100001 (
b110 )
b100 *
b1010011010011000100010101000101010100000010000000100000 +
1,
1/
00
b110 1
b100 2
03
b10 4
b110 8
b100 :
b110 <
b100 =
b10 >
#80000
0!
0,
0/
#85000
1!
b111 $
b101 %
b101010 (
b111 )
1,
0/
b111 1
06
b111 8
b101 :
b111 <
b11 >
#90000
0!
0,
0/
#95000
1!
b1000 $
b110010 (
b1000 )
1,
0/
b1000 1
b1000 8
b1000 <
b100 >
#100000
0!
0,
0/
#105000
1!
b1001 $
b110111 (
b1001 )
1,
0/
b1001 1
b1001 8
b1001 <
b101 >
#110000
0!
0,
0/
#115000
1!
b1010 $
b111100 (
b1010 )
1,
0/
b1010 1
b1010 8
b1010 <
b110 >
#120000
0!
0,
0/
#125000
1!
b1011 $
b111111 (
b1011 )
1,
0/
b1011 1
b1011 8
b1011 <
b111 >
#130000
0!
1#
0,
1.
0/
b1 5
#135000
1!
b1100 $
b1 &
1'
b1000010 (
b1100 )
b1000001010000110101010001001001010101100100010100100000 +
1,
0/
10
b1100 1
13
b1 4
b1100 8
b1100 <
b1000 >
#140000
0!
0,
0/
#145000
1!
b1101 $
b110 %
b111101 (
b1101 )
b101 *
1,
1/
b1101 1
b101 2
16
b1101 8
b110 :
b1101 <
b101 =
b1000 >
#150000
0!
0#
0,
0.
0/
b11 5
#155000
1!
b1110 $
b111 %
b11 &
b111001 (
b1110 )
b110 *
b1010111010000010100100101010100001000000010000000100000 +
1,
1/
b1110 1
b110 2
13
b11 4
b10 5
b1110 8
b111 :
b1110 <
b110 =
b1000 >
#160000
0!
1#
0,
1.
0/
b1 5
#165000
1!
b1111 $
b1000 %
b1 &
b110101 (
b1111 )
b111 *
b1000001010000110101010001001001010101100100010100100000 +
1,
1/
b1111 1
b111 2
13
b1 4
b1111 8
b1000 :
b1111 <
b111 =
b1000 >
#170000
0!
0,
0/
#175000
1!
b10000 $
b1001 %
b110010 (
b10000 )
b1000 *
1,
1/
b10000 1
b1000 2
b10000 8
b1001 :
b10000 <
b1000 =
b1000 >
#180000
0!
0,
0/
#185000
1!
b10001 $
b1010 %
b101111 (
b10001 )
b1001 *
1,
1/
b10001 1
b1001 2
b10001 8
b1010 :
b10001 <
b1001 =
b1000 >
#190000
0!
0#
0,
0.
0/
b11 5
#195000
1!
b10010 $
b1011 %
b11 &
b101100 (
b10010 )
b1010 *
b1010111010000010100100101010100001000000010000000100000 +
1,
1/
b10010 1
b1010 2
13
b11 4
b10 5
b10010 8
b1011 :
b10010 <
b1010 =
b1000 >
#200000
0!
0,
0/
#205000
1!
b10011 $
b1100 %
b10 &
0'
b101010 (
b10011 )
b1011 *
b1010011010011000100010101000101010100000010000000100000 +
1,
1/
00
b10011 1
b1011 2
03
b10 4
b10011 8
b1100 :
b10011 <
b1011 =
b1000 >
#210000
0!
0,
0/
#215000
1!
b10100 $
b1101 %
b101101 (
b10100 )
1,
0/
b10100 1
06
b10100 8
b1101 :
b10100 <
b1001 >
#220000
0!
0,
0/
#225000
1!
b10101 $
b101111 (
b10101 )
1,
0/
b10101 1
b10101 8
b10101 <
b1010 >
